breathing_earth_system_simulator/.DS_Store
breathing_earth_system_simulator/BESS.py
breathing_earth_system_simulator/C3_photosynthesis.py
breathing_earth_system_simulator/C4_fraction.jpeg
breathing_earth_system_simulator/C4_fraction.tif
breathing_earth_system_simulator/C4_photosynthesis.py
breathing_earth_system_simulator/FVC_from_NDVI.py
breathing_earth_system_simulator/LAI_from_NDVI.py
breathing_earth_system_simulator/NDVI_maximum.jpeg
breathing_earth_system_simulator/NDVI_maximum.tif
breathing_earth_system_simulator/NDVI_minimum.jpeg
breathing_earth_system_simulator/NDVI_minimum.tif
breathing_earth_system_simulator/__init__.py
breathing_earth_system_simulator/ball_berry_intercept_C3.jpeg
breathing_earth_system_simulator/ball_berry_intercept_C3.tif
breathing_earth_system_simulator/ball_berry_slope_C3.jpeg
breathing_earth_system_simulator/ball_berry_slope_C3.tif
breathing_earth_system_simulator/ball_berry_slope_C4.jpeg
breathing_earth_system_simulator/ball_berry_slope_C4.tif
breathing_earth_system_simulator/breathing_earth_system_simulator.py
breathing_earth_system_simulator/calculate_VCmax.py
breathing_earth_system_simulator/canopy_energy_balance.py
breathing_earth_system_simulator/canopy_longwave_radiation.py
breathing_earth_system_simulator/canopy_shortwave_radiation.py
breathing_earth_system_simulator/carbon_uptake_efficiency.jpeg
breathing_earth_system_simulator/carbon_uptake_efficiency.tif
breathing_earth_system_simulator/carbon_water_fluxes.py
breathing_earth_system_simulator/check_distribution.py
breathing_earth_system_simulator/constants.py
breathing_earth_system_simulator/interpolate_C3_C4.py
breathing_earth_system_simulator/kn.jpeg
breathing_earth_system_simulator/kn.tif
breathing_earth_system_simulator/load_C4_fraction.py
breathing_earth_system_simulator/load_NDVI_maximum.py
breathing_earth_system_simulator/load_NDVI_minimum.py
breathing_earth_system_simulator/load_ball_berry_intercept_C3.py
breathing_earth_system_simulator/load_ball_berry_slope_C3.py
breathing_earth_system_simulator-1.5.4.dist-info/licenses/LICENSE
breathing_earth_system_simulator-1.5.4.dist-info/METADATA
breathing_earth_system_simulator-1.5.4.dist-info/WHEEL
breathing_earth_system_simulator-1.5.4.dist-info/top_level.txt
breathing_earth_system_simulator-1.5.4.dist-info/RECORD
