Metadata-Version: 2.4
Name: breathing-earth-system-simulator
Version: 1.5.4
Summary: Breathing Earth System Simulator (BESS) Gross Primary Production (GPP) and Evapotranspiration (ET) Model Python
Author-email: Gregory Halverson <gregory.h.halverson@jpl.nasa.gov>
Project-URL: Homepage, https://github.com/JPL-Evapotranspiration-Algorithms/breathing-earth-system-simulator
Classifier: Programming Language :: Python :: 3
Classifier: Operating System :: OS Independent
Requires-Python: >=3.10
License-File: LICENSE
Requires-Dist: FLiESANN>=1.4.1
Requires-Dist: gedi-canopy-height>=1.1.0
Requires-Dist: GEOS5FP>=1.1.1
Requires-Dist: koppengeiger>=1.0.4
Requires-Dist: MODISCI>=1.3.0
Requires-Dist: numpy
Requires-Dist: rasters
Provides-Extra: dev
Requires-Dist: build; extra == "dev"
Requires-Dist: pytest>=6.0; extra == "dev"
Requires-Dist: pytest-cov; extra == "dev"
Requires-Dist: jupyter; extra == "dev"
Requires-Dist: pytest; extra == "dev"
Requires-Dist: twine; extra == "dev"
Dynamic: license-file
